blockstdout/__init__.py
blockstdout/blocker.py
block_stdout-0.3.dist-info/LICENSE
block_stdout-0.3.dist-info/METADATA
block_stdout-0.3.dist-info/WHEEL
block_stdout-0.3.dist-info/top_level.txt
block_stdout-0.3.dist-info/RECORD
