Metadata-Version: 2.1
Name: block-stdout
Version: 0.3
Summary: Python module that blocks the standard output, preventing print statements from being displayed
Author-email: Vignesh Sivanandha Rao <svignesh1793@gmail.com>
License: MIT License
Project-URL: Homepage, https://github.com/thevickypedia/block-stdout
Project-URL: Docs, https://thevickypedia.github.io/block-stdout
Keywords: python,block-stdout
Classifier: Development Status :: 5 - Production/Stable
Classifier: Intended Audience :: Information Technology
Classifier: Operating System :: OS Independent
Classifier: License :: OSI Approved :: MIT License
Classifier: Programming Language :: Python :: 3
Requires-Python: >=3
License-File: LICENSE
Provides-Extra: dev
Requires-Dist: pytest ; extra == 'dev'
